qrsh/__init__.py
qrsh/__init__.py.f05c1f96d612939eb00597cb0468b035.py
qrsh/cli.py
qrsh-0.3.1.dist-info/entry_points.txt
qrsh-0.3.1.dist-info/LICENSE
qrsh-0.3.1.dist-info/WHEEL
qrsh-0.3.1.dist-info/METADATA
qrsh-0.3.1.dist-info/RECORD
